sidcalculator/__init__.py
sidcalculator/calculator.py
sidcalculator-1.0.0.dist-info/LICENSE
sidcalculator-1.0.0.dist-info/METADATA
sidcalculator-1.0.0.dist-info/WHEEL
sidcalculator-1.0.0.dist-info/top_level.txt
sidcalculator-1.0.0.dist-info/RECORD
