Metadata-Version: 2.1
Name: sidcalculator
Version: 1.0.0
Summary: A simple calculator for SID
Author: Shiddhartho Karmaker
Author-email: sid@daffodil.ac
Classifier: Programming Language :: Python :: 3
Classifier: License :: OSI Approved :: MIT License
Classifier: Operating System :: OS Independent
License-File: LICENSE
